MANIFEST.in
README.rst
setup.py
doc/Makefile
doc/__init__.py
doc/conf.py
doc/copying.rst
doc/decorators.rst
doc/index.rst
doc/langacore.kit.cache.memoization.rst
doc/langacore.kit.concurrency.synchronization.rst
doc/langacore.kit.config.FunkyConfigParser.rst
doc/langacore.kit.config.rst
doc/langacore.kit.files.rst
doc/make.bat
doc/overview.rst
doc/theme/ADCtheme/LICENSE
doc/theme/ADCtheme/README.rst
doc/theme/ADCtheme/layout.html
doc/theme/ADCtheme/theme.conf
doc/theme/ADCtheme/static/adctheme.css
doc/theme/ADCtheme/static/breadcrumb_background.png
doc/theme/ADCtheme/static/documentation.png
doc/theme/ADCtheme/static/header_sm_mid.png
doc/theme/ADCtheme/static/scrn1.png
doc/theme/ADCtheme/static/scrn2.png
doc/theme/ADCtheme/static/searchfield_leftcap.png
doc/theme/ADCtheme/static/searchfield_repeat.png
doc/theme/ADCtheme/static/searchfield_rightcap.png
doc/theme/ADCtheme/static/title_background.png
doc/theme/ADCtheme/static/toc.js
doc/theme/ADCtheme/static/triangle_closed.png
doc/theme/ADCtheme/static/triangle_left.png
doc/theme/ADCtheme/static/triangle_open.png
src/langacore/__init__.py
src/langacore.kit.common.egg-info/PKG-INFO
src/langacore.kit.common.egg-info/SOURCES.txt
src/langacore.kit.common.egg-info/dependency_links.txt
src/langacore.kit.common.egg-info/namespace_packages.txt
src/langacore.kit.common.egg-info/requires.txt
src/langacore.kit.common.egg-info/top_level.txt
src/langacore.kit.common.egg-info/zip-safe
src/langacore/kit/__init__.py
src/langacore/kit/cache/__init__.py
src/langacore/kit/cache/memoization.py
src/langacore/kit/collections/__init__.py
src/langacore/kit/collections/orderedset.py
src/langacore/kit/concurrency/__init__.py
src/langacore/kit/concurrency/synchronization.py
src/langacore/kit/config/__init__.py
src/langacore/kit/files/__init__.py
src/langacore/kit/files/finder.py
src/langacore/kit/lang/__init__.py
test/test_memoization.py
test/test_synchronization.py