Metadata-Version: 1.0
Name: langacore.kit.common
Version: 0.2.4
Summary: A library of various simple common routines that keep being rewritten all over again in every project I'm working on.
Home-page: http://packages.python.org/langacore.kit.common/
Author: LangaCore, Lukasz Langa
Author-email: support@langacore.org, lukasz@langa.pl
License: GPL v3
Platform: any
Classifier: Development Status :: 3 - Alpha
Classifier: Intended Audience :: Developers
Classifier: License :: OSI Approved :: GNU General Public License (GPL)
Classifier: Natural Language :: English
Classifier: Operating System :: POSIX
Classifier: Operating System :: MacOS :: MacOS X
Classifier: Operating System :: Microsoft :: Windows :: Windows NT/2000
Classifier: Programming Language :: Python
Classifier: Programming Language :: Python :: 2.7
Classifier: Topic :: Software Development :: Libraries :: Python Modules
